slacker/__init__.py
slacker/base.py
slacker/dispatch.py
slacker/func.py
slacker/persist.py
slacker/sentinel.py
slacker/text.py
slacker/service/__init__.py
slacker/service/base.py
slacker/service/slack.py
slacker/service/txn.py
faastm-0.1.1.dist-info/LICENCE.md
faastm-0.1.1.dist-info/METADATA
faastm-0.1.1.dist-info/WHEEL
faastm-0.1.1.dist-info/entry_points.txt
faastm-0.1.1.dist-info/top_level.txt
faastm-0.1.1.dist-info/RECORD
