Metadata-Version: 2.1
Name: faastm
Version: 0.1.1
Summary: Experimental one-cell STM for FaaS
Home-page: UNKNOWN
Author: jang
Author-email: faastm@ioctl.org
License: Apache 2
Platform: UNKNOWN
Classifier: Development Status :: 4 - Beta
Classifier: Intended Audience :: Developers
Classifier: License :: OSI Approved :: Apache Software License
Classifier: Programming Language :: Python
Classifier: Programming Language :: Python :: 3
Classifier: Programming Language :: Python :: 3.6
Classifier: Programming Language :: Python :: 3.7
Classifier: Topic :: Communications :: Chat
Requires-Dist: cachetools
Requires-Dist: dill
Requires-Dist: fdk
Requires-Dist: oci (>=2.2.18)
Requires-Dist: requests
